cyfes/wrapper.c
cyfes/wrapper_f32.cpython-39-x86_64-linux-gnu.so
cyfes/__main__.py
cyfes/__init__.py
cyfes/utils.py
cyfes/wrapper_f32.c
cyfes/wrapper.cpython-39-x86_64-linux-gnu.so
cyfes/kernels/__init__.py
cyfes/kernels/FES.cuh
cyfes/kernels/FES_f32.cuh
CyFES.libs/libcudart-80664282.so.10.2.89
CyFES.libs/libgomp-a34b3233.so.1.0.0
CyFES-3.5.dist-info/WHEEL
CyFES-3.5.dist-info/LICENSE
CyFES-3.5.dist-info/RECORD
CyFES-3.5.dist-info/top_level.txt
CyFES-3.5.dist-info/METADATA
CyFES-3.5.data/data/cyfes/libcufes.so
CyFES-3.5.data/data/cyfes/libcufes.1.so
CyFES-3.5.data/data/cyfes/FES.cuh
CyFES-3.5.data/data/cyfes/FES_f32.cuh
