Metadata-Version: 2.1
Name: CyFES
Version: 3.5
Summary: Cython Based Fast FES Calculation Toolkit.
Home-page: https://gitee.com/dechin/cy-fes
Author: Dechin CHEN
Author-email: dechin.phy@gmail.com
License: MIT
Platform: any
Requires-Dist: cython
Requires-Dist: numpy (<=1.21.6) ; python_version <= "3.7"
Requires-Dist: numpy (<1.28,>=1.23) ; python_version > "3.7"
